mpolar/__init__.py
mpolar/exception.py
mpolar/list_format.py
mpolar/polar.py
mpolar/propulsion.py
mpolar/py.typed
mpolar/schema.py
mpolar/table_format.py
test/__init__.py
test/common.py
test/test_parse.py
tools/__init__.py
tools/csv2nc.py
tools/nc2csv.py
mpolar-1.6.2.dist-info/METADATA
mpolar-1.6.2.dist-info/WHEEL
mpolar-1.6.2.dist-info/top_level.txt
mpolar-1.6.2.dist-info/RECORD
